artek/__init__.py
artek/images/__init__.py
artek/images/apps.py
artek/images/compat.py
artek/images/models.py
artek/images/specs.py
artek/images/urls.py
artek/images/utils.py
artek/images/views.py
artek/images/tests/__init__.py
artek/images/tests/test.py
artek/images/tests/tests.py
artek/images/tests/urls.py
artek_images-3.0.3.dist-info/METADATA
artek_images-3.0.3.dist-info/WHEEL
artek_images-3.0.3.dist-info/top_level.txt
artek_images-3.0.3.dist-info/RECORD
