Metadata-Version: 2.1
Name: artek-images
Version: 3.0.3
Summary: an app for managing collections of images associated with a content object
Home-page: http://github.com/AHDCreative/artek-images/
Author: Artek
Author-email: luca@ahd-creative.com
License: MIT
Platform: UNKNOWN
Classifier: Development Status :: 5 - Production/Stable
Classifier: Environment :: Web Environment
Classifier: Framework :: Django
Classifier: Framework :: Django :: 1.11
Classifier: Framework :: Django :: 2.0
Classifier: Intended Audience :: Developers
Classifier: License :: OSI Approved :: MIT License
Classifier: Operating System :: OS Independent
Classifier: Programming Language :: Python
Classifier: Programming Language :: Python :: 2
Classifier: Programming Language :: Python :: 2.7
Classifier: Programming Language :: Python :: 3
Classifier: Programming Language :: Python :: 3.4
Classifier: Programming Language :: Python :: 3.5
Classifier: Programming Language :: Python :: 3.6
Classifier: Programming Language :: Python :: 3.7
Classifier: Topic :: Software Development :: Libraries :: Python Modules
Requires-Dist: django (>=1.11)
Requires-Dist: django-imagekit (>=3.2.7)
Requires-Dist: pilkit (>=1.1.13)
Requires-Dist: pillow (>=3.3.0)
Requires-Dist: pytz (>=2016.6.1)
